streamlit_pdf_reader/__init__.py
streamlit_pdf_reader/frontend/build/asset-manifest.json
streamlit_pdf_reader/frontend/build/bootstrap.min.css
streamlit_pdf_reader/frontend/build/index.html
streamlit_pdf_reader/frontend/build/static/css/main.bb02f91d.css
streamlit_pdf_reader/frontend/build/static/css/main.bb02f91d.css.map
streamlit_pdf_reader/frontend/build/static/js/main.cf31578e.js
streamlit_pdf_reader/frontend/build/static/js/main.cf31578e.js.LICENSE.txt
streamlit_pdf_reader/frontend/build/static/js/main.cf31578e.js.map
streamlit_pdf_reader-0.0.5.dist-info/LICENSE
streamlit_pdf_reader-0.0.5.dist-info/METADATA
streamlit_pdf_reader-0.0.5.dist-info/WHEEL
streamlit_pdf_reader-0.0.5.dist-info/top_level.txt
streamlit_pdf_reader-0.0.5.dist-info/RECORD
