Metadata-Version: 2.1
Name: streamlit_pdf_reader
Version: 0.0.5
Summary: Streamlit pdf reader component
Home-page: https://github.com/B4PT0R/streamlit_pdf_reader
Author: Baptiste Ferrand
Author-email: bferrand.maths@gmail.com
Requires-Python: >=3.7
License-File: LICENSE
Requires-Dist: streamlit>=0.63
